[ 
{
    "id":1,
    "nombre": "Arandanos",
    "precio": 780,
    "stock": 10,
    "imgUrl": "/images/aran.png",
    "sabor": "Dulces",
    "categoria":"1"
},
{
    "id":2,
    "nombre": "Frutilla",
    "precio": 780,
    "stock": 20,
    "imgUrl": "/images/fru.png",
    "sabor": "Dulces",
    "categoria":"1"
},
{
    "id":3,
    "nombre": "Limon",
    "precio": 780,
    "stock": 12,
    "imgUrl": "/images/limon.png",
    "sabor": "Dulces",
    "categoria":"1"
},
{
    "id":4,
    "nombre": "Cafe",
    "precio": 780,
    "stock": 13,
    "imgUrl": "/images/cafe.png",
    "sabor": "Dulces",
    "categoria":"1"
},
{
    "id":5,
    "nombre": "Queso",
    "precio": 780,
    "stock": 15,
    "imgUrl": "/images/queso.png",
    "sabor": "Saladas",
    "categoria":"2"
}
]
